lazy_import/VERSION
lazy_import/__init__.py
lazy_import/lazy_class.py
lazy_import/test_lazy.py
lazy_import/test_lazy_class.py
lazy_import_plus/VERSION
lazy_import_plus/__init__.py
lazy_import_plus/lazy_class.py
lazy_import_plus/test_lazy.py
lazy_import_plus/test_lazy_class.py
lazy_import_plus-0.0.2.dist-info/LICENSE
lazy_import_plus-0.0.2.dist-info/METADATA
lazy_import_plus-0.0.2.dist-info/WHEEL
lazy_import_plus-0.0.2.dist-info/top_level.txt
lazy_import_plus-0.0.2.dist-info/RECORD
